my_distributions2020/Binomialdistribution.py
my_distributions2020/Gaussiandistribution.py
my_distributions2020/Generaldistribution.py
my_distributions2020/__init__.py
my_distributions2020-0.1.dist-info/METADATA
my_distributions2020-0.1.dist-info/WHEEL
my_distributions2020-0.1.dist-info/top_level.txt
my_distributions2020-0.1.dist-info/RECORD
